{
  "Last_name_ru": "ГЕРАСИМОВА",
  "First_name_ru": "МАРИЯ",
  "Last_name_en": "",
  "First_name_en": "",
  "Licence_number": "40 13 965611",
  "Issue_date": "02.06.2014",
  "Expiration_date": "",
  "Driver_class": "",
  "Birth_date": "28.04.2000",
  "Birth_place_ru": "САНКТ-ПЕТЕРБУРГ",
  "Birth_place_en": "",
  "Issue_organization_ru": "ТП №13 ОТДЕЛА УФМС РОССИИ ПО САНКТ-ПЕТЕРБУРГУ И ЛЕНИНГРАДСКОЙ ОБЛ. В ВЫБОРГСКОМ Р-НЕ Г. САНКТ-ПЕТЕРБУРГА",
  "Issue_organization_en": "",
  "Living_region_ru": "",
  "Living_region_en": "",
  "Middle_name_ru": "ВЛАДИМИРОВНА",
  "Sex_ru": "Ж",
  "Sex_en": "",
  "Issue_organisation_code": "780-013",
  "Middle_name_en": ""
}